MANIFEST.in
meta.json
setup.py
en_writer_inclusivity/__init__.py
en_writer_inclusivity/meta.json
en_writer_inclusivity.egg-info/PKG-INFO
en_writer_inclusivity.egg-info/SOURCES.txt
en_writer_inclusivity.egg-info/dependency_links.txt
en_writer_inclusivity.egg-info/not-zip-safe
en_writer_inclusivity.egg-info/requires.txt
en_writer_inclusivity.egg-info/top_level.txt
en_writer_inclusivity/en_writer_inclusivity-2.3.1.1.1.3/meta.json
en_writer_inclusivity/en_writer_inclusivity-2.3.1.1.1.3/tokenizer
en_writer_inclusivity/en_writer_inclusivity-2.3.1.1.1.3/ner/cfg
en_writer_inclusivity/en_writer_inclusivity-2.3.1.1.1.3/ner/model
en_writer_inclusivity/en_writer_inclusivity-2.3.1.1.1.3/ner/moves
en_writer_inclusivity/en_writer_inclusivity-2.3.1.1.1.3/parser/cfg
en_writer_inclusivity/en_writer_inclusivity-2.3.1.1.1.3/parser/model
en_writer_inclusivity/en_writer_inclusivity-2.3.1.1.1.3/parser/moves
en_writer_inclusivity/en_writer_inclusivity-2.3.1.1.1.3/tagger/cfg
en_writer_inclusivity/en_writer_inclusivity-2.3.1.1.1.3/tagger/model
en_writer_inclusivity/en_writer_inclusivity-2.3.1.1.1.3/tagger/tag_map
en_writer_inclusivity/en_writer_inclusivity-2.3.1.1.1.3/vocab/key2row
en_writer_inclusivity/en_writer_inclusivity-2.3.1.1.1.3/vocab/lookups.bin
en_writer_inclusivity/en_writer_inclusivity-2.3.1.1.1.3/vocab/lookups_extra.bin
en_writer_inclusivity/en_writer_inclusivity-2.3.1.1.1.3/vocab/strings.json
en_writer_inclusivity/en_writer_inclusivity-2.3.1.1.1.3/vocab/vectors